{"filename":"data.json","collections":[{"name":"bookings","data":[{"name":"dsfsd","email":"sad@ad","genre":"fantasy","time":"Once a week","when":"home","meta":{"revision":0,"created":1636032870656,"version":0},"$loki":1},{"name":"dsfsd","email":"sad@ad","genre":"detective","time":"2/3 days a week","when":"cafe","meta":{"revision":0,"created":1636032882582,"version":0},"$loki":2},{"name":"dsfsd","email":"sad@ad","genre":"Romance","time":"Once a week","when":"work","meta":{"revision":0,"created":1636032888585,"version":0},"$loki":3},{"name":"dfs","email":"fsd@gfs","genre":"Science Fiction","time":"Once a week","when":"work","meta":{"revision":0,"created":1636033161138,"version":0},"$loki":4},{"name":"dfs","email":"fsd@gfs","genre":"Romance","time":"Once a week","when":"work","meta":{"revision":0,"created":1636033231221,"version":0},"$loki":5},{"name":"dfs","email":"fsd@gfs","genre":"Mystery","time":"Once a week","when":"work","meta":{"revision":0,"created":1636033237915,"version":0},"$loki":6},{"name":"dfs","email":"fsd@gfs","genre":"Detective Story","time":"Once a week","when":"work","meta":{"revision":0,"created":1636033243473,"version":0},"$loki":7},{"name":"dfs","email":"fsd@gfs","genre":"Thriller","time":"Once a week","when":"work","meta":{"revision":0,"created":1636033277579,"version":0},"$loki":8},{"name":"dfs","email":"fsd@gfs","genre":"Science Fiction","time":"Once a week","when":"work","meta":{"revision":0,"created":1636033281803,"version":0},"$loki":9},{"name":"dfs","email":"fsd@gfs","genre":"Mystery","time":"Once a week","when":"work","meta":{"revision":0,"created":1636033285688,"version":0},"$loki":10},{"name":"dfs","email":"fsd@gfs","genre":"Science Fiction","time":"Once a week","when":"work","meta":{"revision":0,"created":1636033288100,"version":0},"$loki":11},{"name":"dfs","email":"fsd@gfs","genre":"Science Fiction","time":"Once a week","when":"work","meta":{"revision":0,"created":1636033292021,"version":0},"$loki":12},{"name":"dfs","email":"fsd@gfs","genre":"Science Fiction","time":"Once a week","when":"work","meta":{"revision":0,"created":1636033298498,"version":0},"$loki":13},{"name":"dfs","email":"fsd@gfs","genre":"Science Fiction","time":"Once a week","when":"work","meta":{"revision":0,"created":1636033300180,"version":0},"$loki":14},{"name":"d","email":"vcx@fx","genre":"Science Fiction","time":"Everyday","when":"home","meta":{"revision":0,"created":1636033369392,"version":0},"$loki":15},{"name":"d","email":"vcx@fx","genre":"Science Fiction","time":"Everyday","when":"home","meta":{"revision":0,"created":1636033375417,"version":0},"$loki":16},{"name":"d","email":"vcx@fx","genre":"Science Fiction","time":"Everyday","when":"home","meta":{"revision":0,"created":1636033376014,"version":0},"$loki":17},{"name":"d","email":"vcx@fx","genre":"Fantasy","time":"Everyday","when":"home","meta":{"revision":0,"created":1636033381072,"version":0},"$loki":18},{"name":"d","email":"vcx@fx","genre":"Fantasy","time":"Everyday","when":"home","meta":{"revision":0,"created":1636033382391,"version":0},"$loki":19},{"name":"d","email":"vcx@fx","genre":"Fantasy","time":"Everyday","when":"home","meta":{"revision":0,"created":1636033382931,"version":0},"$loki":20},{"name":"d","email":"vcx@fx","genre":"Fantasy","time":"Everyday","when":"home","meta":{"revision":0,"created":1636033386931,"version":0},"$loki":21},{"name":"d","email":"vcx@fx","genre":"Detective Story","time":"2/3 days a week","when":"cafe","meta":{"revision":0,"created":1636033406385,"version":0},"$loki":22},{"name":"d","email":"vcx@fx","genre":"Detective Story","time":"2/3 days a week","when":"cafe","meta":{"revision":0,"created":1636033406989,"version":0},"$loki":23},{"name":"d","email":"vcx@fx","genre":"Detective Story","time":"2/3 days a week","when":"cafe","meta":{"revision":0,"created":1636033407534,"version":0},"$loki":24},{"name":"d","email":"vcx@fx","genre":"Thriller","time":"2/3 days a week","when":"cafe","meta":{"revision":0,"created":1636033418338,"version":0},"$loki":25},{"name":"d","email":"vcx@fx","genre":"Thriller","time":"2/3 days a week","when":"cafe","meta":{"revision":0,"created":1636033418756,"version":0},"$loki":26},{"name":"d","email":"vcx@fx","genre":"Thriller","time":"2/3 days a week","when":"cafe","meta":{"revision":0,"created":1636033427475,"version":0},"$loki":27}],"idIndex":null,"binaryIndices":{},"constraints":null,"uniqueNames":[],"transforms":{},"objType":"bookings","dirty":false,"cachedIndex":null,"cachedBinaryIndex":null,"cachedData":null,"adaptiveBinaryIndices":true,"transactional":false,"cloneObjects":false,"cloneMethod":"parse-stringify","asyncListeners":false,"disableMeta":false,"disableChangesApi":true,"disableDeltaChangesApi":true,"autoupdate":false,"serializableIndices":true,"disableFreeze":true,"ttl":null,"maxId":27,"DynamicViews":[],"events":{"insert":[],"update":[],"pre-insert":[],"pre-update":[],"close":[],"flushbuffer":[],"error":[],"delete":[null],"warning":[null]},"changes":[],"dirtyIds":[]}],"databaseVersion":1.5,"engineVersion":1.5,"autosave":true,"autosaveInterval":4000,"autosaveHandle":null,"throttledSaves":true,"options":{"autoload":true,"autosave":true,"autosaveInterval":4000,"serializationMethod":"normal","destructureDelimiter":"$<\n","recursiveWait":true,"recursiveWaitLimit":false,"recursiveWaitLimitDuration":2000,"started":1636032844072},"persistenceMethod":"fs","persistenceAdapter":null,"verbose":false,"events":{"init":[null],"loaded":[],"flushChanges":[],"close":[],"changes":[],"warning":[]},"ENV":"NODEJS"}